package android.support.v7.widget;

import android.content.Context;
import android.graphics.Canvas;
import android.graphics.Rect;
import android.graphics.drawable.Drawable;
import android.os.Build;
import android.support.annotation.NonNull;
import android.support.v4.graphics.drawable.DrawableCompat;
import android.support.v4.view.ViewPropertyAnimatorCompat;
import android.support.v4.widget.ListViewAutoScrollHelper;
import android.support.v7.appcompat.R;
import android.support.v7.graphics.drawable.DrawableWrapper;
import android.view.MotionEvent;
import android.view.View;
import android.view.ViewGroup;
import android.widget.AbsListView;
import android.widget.ListAdapter;
import android.widget.ListView;
import java.lang.reflect.Field;

class DropDownListView extends ListView {
  public static final int INVALID_POSITION = -1;
  
  public static final int NO_POSITION = -1;
  
  private ViewPropertyAnimatorCompat mClickAnimation;
  
  private boolean mDrawsInPressedState;
  
  private boolean mHijackFocus;
  
  private Field mIsChildViewEnabled;
  
  private boolean mListSelectionHidden;
  
  private int mMotionPosition;
  
  ResolveHoverRunnable mResolveHoverRunnable;
  
  private ListViewAutoScrollHelper mScrollHelper;
  
  private int mSelectionBottomPadding = 0;
  
  private int mSelectionLeftPadding = 0;
  
  private int mSelectionRightPadding = 0;
  
  private int mSelectionTopPadding = 0;
  
  private GateKeeperDrawable mSelector;
  
  private final Rect mSelectorRect = new Rect();
  
  DropDownListView(Context paramContext, boolean paramBoolean) {
    super(paramContext, null, R.attr.dropDownListViewStyle);
    this.mHijackFocus = paramBoolean;
    setCacheColorHint(0);
    try {
      this.mIsChildViewEnabled = AbsListView.class.getDeclaredField("mIsChildViewEnabled");
      this.mIsChildViewEnabled.setAccessible(true);
      return;
    } catch (NoSuchFieldException noSuchFieldException) {
      noSuchFieldException.printStackTrace();
      return;
    } 
  }
  
  private void clearPressedItem() {
    this.mDrawsInPressedState = false;
    setPressed(false);
    drawableStateChanged();
    View view = getChildAt(this.mMotionPosition - getFirstVisiblePosition());
    if (view != null)
      view.setPressed(false); 
    if (this.mClickAnimation != null) {
      this.mClickAnimation.cancel();
      this.mClickAnimation = null;
    } 
  }
  
  private void clickPressedItem(View paramView, int paramInt) {
    performItemClick(paramView, paramInt, getItemIdAtPosition(paramInt));
  }
  
  private void drawSelectorCompat(Canvas paramCanvas) {
    if (!this.mSelectorRect.isEmpty()) {
      Drawable drawable = getSelector();
      if (drawable != null) {
        drawable.setBounds(this.mSelectorRect);
        drawable.draw(paramCanvas);
      } 
    } 
  }
  
  private void positionSelectorCompat(int paramInt, View paramView) {
    Rect rect = this.mSelectorRect;
    rect.set(paramView.getLeft(), paramView.getTop(), paramView.getRight(), paramView.getBottom());
    rect.left -= this.mSelectionLeftPadding;
    rect.top -= this.mSelectionTopPadding;
    rect.right += this.mSelectionRightPadding;
    rect.bottom += this.mSelectionBottomPadding;
    try {
      boolean bool = this.mIsChildViewEnabled.getBoolean(this);
      if (paramView.isEnabled() != bool) {
        this.mIsChildViewEnabled.set(this, Boolean.valueOf(bool ^ true));
        if (paramInt != -1) {
          refreshDrawableState();
          return;
        } 
      } 
    } catch (IllegalAccessException illegalAccessException) {
      illegalAccessException.printStackTrace();
    } 
  }
  
  private void positionSelectorLikeFocusCompat(int paramInt, View paramView) {
    boolean bool1;
    Drawable drawable = getSelector();
    boolean bool2 = true;
    if (drawable != null && paramInt != -1) {
      bool1 = true;
    } else {
      bool1 = false;
    } 
    if (bool1)
      drawable.setVisible(false, false); 
    positionSelectorCompat(paramInt, paramView);
    if (bool1) {
      Rect rect = this.mSelectorRect;
      float f1 = rect.exactCenterX();
      float f2 = rect.exactCenterY();
      if (getVisibility() != 0)
        bool2 = false; 
      drawable.setVisible(bool2, false);
      DrawableCompat.setHotspot(drawable, f1, f2);
    } 
  }
  
  private void positionSelectorLikeTouchCompat(int paramInt, View paramView, float paramFloat1, float paramFloat2) {
    positionSelectorLikeFocusCompat(paramInt, paramView);
    Drawable drawable = getSelector();
    if (drawable != null && paramInt != -1)
      DrawableCompat.setHotspot(drawable, paramFloat1, paramFloat2); 
  }
  
  private void setPressedItem(View paramView, int paramInt, float paramFloat1, float paramFloat2) {
    this.mDrawsInPressedState = true;
    if (Build.VERSION.SDK_INT >= 21)
      drawableHotspotChanged(paramFloat1, paramFloat2); 
    if (!isPressed())
      setPressed(true); 
    layoutChildren();
    if (this.mMotionPosition != -1) {
      View view = getChildAt(this.mMotionPosition - getFirstVisiblePosition());
      if (view != null && view != paramView && view.isPressed())
        view.setPressed(false); 
    } 
    this.mMotionPosition = paramInt;
    float f1 = paramView.getLeft();
    float f2 = paramView.getTop();
    if (Build.VERSION.SDK_INT >= 21)
      paramView.drawableHotspotChanged(paramFloat1 - f1, paramFloat2 - f2); 
    if (!paramView.isPressed())
      paramView.setPressed(true); 
    positionSelectorLikeTouchCompat(paramInt, paramView, paramFloat1, paramFloat2);
    setSelectorEnabled(false);
    refreshDrawableState();
  }
  
  private void setSelectorEnabled(boolean paramBoolean) {
    if (this.mSelector != null)
      this.mSelector.setEnabled(paramBoolean); 
  }
  
  private boolean touchModeDrawsInPressedStateCompat() {
    return this.mDrawsInPressedState;
  }
  
  private void updateSelectorStateCompat() {
    Drawable drawable = getSelector();
    if (drawable != null && touchModeDrawsInPressedStateCompat() && isPressed())
      drawable.setState(getDrawableState()); 
  }
  
  protected void dispatchDraw(Canvas paramCanvas) {
    drawSelectorCompat(paramCanvas);
    super.dispatchDraw(paramCanvas);
  }
  
  protected void drawableStateChanged() {
    if (this.mResolveHoverRunnable != null)
      return; 
    super.drawableStateChanged();
    setSelectorEnabled(true);
    updateSelectorStateCompat();
  }
  
  public boolean hasFocus() {
    return (this.mHijackFocus || super.hasFocus());
  }
  
  public boolean hasWindowFocus() {
    return (this.mHijackFocus || super.hasWindowFocus());
  }
  
  public boolean isFocused() {
    return (this.mHijackFocus || super.isFocused());
  }
  
  public boolean isInTouchMode() {
    return ((this.mHijackFocus && this.mListSelectionHidden) || super.isInTouchMode());
  }
  
  public int lookForSelectablePosition(int paramInt, boolean paramBoolean) {
    ListAdapter listAdapter = getAdapter();
    if (listAdapter != null) {
      if (isInTouchMode())
        return -1; 
      int i = listAdapter.getCount();
      if (!getAdapter().areAllItemsEnabled()) {
        int j;
        if (paramBoolean) {
          paramInt = Math.max(0, paramInt);
          while (true) {
            j = paramInt;
            if (paramInt < i) {
              j = paramInt;
              if (!listAdapter.isEnabled(paramInt)) {
                paramInt++;
                continue;
              } 
            } 
            break;
          } 
        } else {
          paramInt = Math.min(paramInt, i - 1);
          while (true) {
            j = paramInt;
            if (paramInt >= 0) {
              j = paramInt;
              if (!listAdapter.isEnabled(paramInt)) {
                paramInt--;
                continue;
              } 
            } 
            break;
          } 
        } 
        return (j >= 0) ? ((j >= i) ? -1 : j) : -1;
      } 
      return (paramInt >= 0) ? ((paramInt >= i) ? -1 : paramInt) : -1;
    } 
    return -1;
  }
  
  public int measureHeightOfChildrenCompat(int paramInt1, int paramInt2, int paramInt3, int paramInt4, int paramInt5) {
    paramInt2 = getListPaddingTop();
    paramInt3 = getListPaddingBottom();
    getListPaddingLeft();
    getListPaddingRight();
    int i = getDividerHeight();
    Drawable drawable = getDivider();
    ListAdapter listAdapter = getAdapter();
    if (listAdapter == null)
      return paramInt2 + paramInt3; 
    if (i <= 0 || drawable == null)
      i = 0; 
    int m = listAdapter.getCount();
    paramInt3 = paramInt2 + paramInt3;
    drawable = null;
    int j = 0;
    int k = 0;
    for (paramInt2 = 0; j < m; paramInt2 = i1) {
      int i1 = listAdapter.getItemViewType(j);
      int n = k;
      if (i1 != k) {
        drawable = null;
        n = i1;
      } 
      View view2 = listAdapter.getView(j, (View)drawable, (ViewGroup)this);
      ViewGroup.LayoutParams layoutParams2 = view2.getLayoutParams();
      ViewGroup.LayoutParams layoutParams1 = layoutParams2;
      if (layoutParams2 == null) {
        layoutParams1 = generateDefaultLayoutParams();
        view2.setLayoutParams(layoutParams1);
      } 
      if (layoutParams1.height > 0) {
        k = View.MeasureSpec.makeMeasureSpec(layoutParams1.height, 1073741824);
      } else {
        k = View.MeasureSpec.makeMeasureSpec(0, 0);
      } 
      view2.measure(paramInt1, k);
      view2.forceLayout();
      k = paramInt3;
      if (j > 0)
        k = paramInt3 + i; 
      paramInt3 = k + view2.getMeasuredHeight();
      if (paramInt3 >= paramInt4) {
        paramInt1 = paramInt4;
        if (paramInt5 >= 0) {
          paramInt1 = paramInt4;
          if (j > paramInt5) {
            paramInt1 = paramInt4;
            if (paramInt2 > 0) {
              paramInt1 = paramInt4;
              if (paramInt3 != paramInt4)
                paramInt1 = paramInt2; 
            } 
          } 
        } 
        return paramInt1;
      } 
      i1 = paramInt2;
      if (paramInt5 >= 0) {
        i1 = paramInt2;
        if (j >= paramInt5)
          i1 = paramInt3; 
      } 
      j++;
      k = n;
      View view1 = view2;
    } 
    return paramInt3;
  }
  
  protected void onDetachedFromWindow() {
    this.mResolveHoverRunnable = null;
    super.onDetachedFromWindow();
  }
  
  public boolean onForwardedEvent(MotionEvent paramMotionEvent, int paramInt) {
    // Byte code:
    //   0: aload_1
    //   1: invokevirtual getActionMasked : ()I
    //   4: istore_3
    //   5: iload_3
    //   6: tableswitch default -> 32, 1 -> 54, 2 -> 48, 3 -> 40
    //   32: iconst_0
    //   33: istore_2
    //   34: iconst_1
    //   35: istore #6
    //   37: goto -> 151
    //   40: iconst_0
    //   41: istore_2
    //   42: iconst_0
    //   43: istore #6
    //   45: goto -> 151
    //   48: iconst_1
    //   49: istore #6
    //   51: goto -> 57
    //   54: iconst_0
    //   55: istore #6
    //   57: aload_1
    //   58: iload_2
    //   59: invokevirtual findPointerIndex : (I)I
    //   62: istore #4
    //   64: iload #4
    //   66: ifge -> 72
    //   69: goto -> 40
    //   72: aload_1
    //   73: iload #4
    //   75: invokevirtual getX : (I)F
    //   78: f2i
    //   79: istore_2
    //   80: aload_1
    //   81: iload #4
    //   83: invokevirtual getY : (I)F
    //   86: f2i
    //   87: istore #4
    //   89: aload_0
    //   90: iload_2
    //   91: iload #4
    //   93: invokevirtual pointToPosition : (II)I
    //   96: istore #5
    //   98: iload #5
    //   100: iconst_m1
    //   101: if_icmpne -> 109
    //   104: iconst_1
    //   105: istore_2
    //   106: goto -> 151
    //   109: aload_0
    //   110: iload #5
    //   112: aload_0
    //   113: invokevirtual getFirstVisiblePosition : ()I
    //   116: isub
    //   117: invokevirtual getChildAt : (I)Landroid/view/View;
    //   120: astore #7
    //   122: aload_0
    //   123: aload #7
    //   125: iload #5
    //   127: iload_2
    //   128: i2f
    //   129: iload #4
    //   131: i2f
    //   132: invokespecial setPressedItem : (Landroid/view/View;IFF)V
    //   135: iload_3
    //   136: iconst_1
    //   137: if_icmpne -> 32
    //   140: aload_0
    //   141: aload #7
    //   143: iload #5
    //   145: invokespecial clickPressedItem : (Landroid/view/View;I)V
    //   148: goto -> 32
    //   151: iload #6
    //   153: ifeq -> 160
    //   156: iload_2
    //   157: ifeq -> 164
    //   160: aload_0
    //   161: invokespecial clearPressedItem : ()V
    //   164: iload #6
    //   166: ifeq -> 210
    //   169: aload_0
    //   170: getfield mScrollHelper : Landroid/support/v4/widget/ListViewAutoScrollHelper;
    //   173: ifnonnull -> 188
    //   176: aload_0
    //   177: new android/support/v4/widget/ListViewAutoScrollHelper
    //   180: dup
    //   181: aload_0
    //   182: invokespecial <init> : (Landroid/widget/ListView;)V
    //   185: putfield mScrollHelper : Landroid/support/v4/widget/ListViewAutoScrollHelper;
    //   188: aload_0
    //   189: getfield mScrollHelper : Landroid/support/v4/widget/ListViewAutoScrollHelper;
    //   192: iconst_1
    //   193: invokevirtual setEnabled : (Z)Landroid/support/v4/widget/AutoScrollHelper;
    //   196: pop
    //   197: aload_0
    //   198: getfield mScrollHelper : Landroid/support/v4/widget/ListViewAutoScrollHelper;
    //   201: aload_0
    //   202: aload_1
    //   203: invokevirtual onTouch : (Landroid/view/View;Landroid/view/MotionEvent;)Z
    //   206: pop
    //   207: iload #6
    //   209: ireturn
    //   210: aload_0
    //   211: getfield mScrollHelper : Landroid/support/v4/widget/ListViewAutoScrollHelper;
    //   214: ifnull -> 226
    //   217: aload_0
    //   218: getfield mScrollHelper : Landroid/support/v4/widget/ListViewAutoScrollHelper;
    //   221: iconst_0
    //   222: invokevirtual setEnabled : (Z)Landroid/support/v4/widget/AutoScrollHelper;
    //   225: pop
    //   226: iload #6
    //   228: ireturn
  }
  
  public boolean onHoverEvent(@NonNull MotionEvent paramMotionEvent) {
    if (Build.VERSION.SDK_INT < 26)
      return super.onHoverEvent(paramMotionEvent); 
    int i = paramMotionEvent.getActionMasked();
    if (i == 10 && this.mResolveHoverRunnable == null) {
      this.mResolveHoverRunnable = new ResolveHoverRunnable();
      this.mResolveHoverRunnable.post();
    } 
    boolean bool = super.onHoverEvent(paramMotionEvent);
    if (i == 9 || i == 7) {
      i = pointToPosition((int)paramMotionEvent.getX(), (int)paramMotionEvent.getY());
      if (i != -1 && i != getSelectedItemPosition()) {
        View view = getChildAt(i - getFirstVisiblePosition());
        if (view.isEnabled())
          setSelectionFromTop(i, view.getTop() - getTop()); 
        updateSelectorStateCompat();
      } 
      return bool;
    } 
    setSelection(-1);
    return bool;
  }
  
  public boolean onTouchEvent(MotionEvent paramMotionEvent) {
    if (paramMotionEvent.getAction() == 0)
      this.mMotionPosition = pointToPosition((int)paramMotionEvent.getX(), (int)paramMotionEvent.getY()); 
    if (this.mResolveHoverRunnable != null)
      this.mResolveHoverRunnable.cancel(); 
    return super.onTouchEvent(paramMotionEvent);
  }
  
  void setListSelectionHidden(boolean paramBoolean) {
    this.mListSelectionHidden = paramBoolean;
  }
  
  public void setSelector(Drawable paramDrawable) {
    GateKeeperDrawable gateKeeperDrawable;
    if (paramDrawable != null) {
      gateKeeperDrawable = new GateKeeperDrawable(paramDrawable);
    } else {
      gateKeeperDrawable = null;
    } 
    this.mSelector = gateKeeperDrawable;
    super.setSelector((Drawable)this.mSelector);
    Rect rect = new Rect();
    if (paramDrawable != null)
      paramDrawable.getPadding(rect); 
    this.mSelectionLeftPadding = rect.left;
    this.mSelectionTopPadding = rect.top;
    this.mSelectionRightPadding = rect.right;
    this.mSelectionBottomPadding = rect.bottom;
  }
  
  private static class GateKeeperDrawable extends DrawableWrapper {
    private boolean mEnabled = true;
    
    GateKeeperDrawable(Drawable param1Drawable) {
      super(param1Drawable);
    }
    
    public void draw(Canvas param1Canvas) {
      if (this.mEnabled)
        super.draw(param1Canvas); 
    }
    
    void setEnabled(boolean param1Boolean) {
      this.mEnabled = param1Boolean;
    }
    
    public void setHotspot(float param1Float1, float param1Float2) {
      if (this.mEnabled)
        super.setHotspot(param1Float1, param1Float2); 
    }
    
    public void setHotspotBounds(int param1Int1, int param1Int2, int param1Int3, int param1Int4) {
      if (this.mEnabled)
        super.setHotspotBounds(param1Int1, param1Int2, param1Int3, param1Int4); 
    }
    
    public boolean setState(int[] param1ArrayOfint) {
      return this.mEnabled ? super.setState(param1ArrayOfint) : false;
    }
    
    public boolean setVisible(boolean param1Boolean1, boolean param1Boolean2) {
      return this.mEnabled ? super.setVisible(param1Boolean1, param1Boolean2) : false;
    }
  }
  
  private class ResolveHoverRunnable implements Runnable {
    public void cancel() {
      DropDownListView.this.mResolveHoverRunnable = null;
      DropDownListView.this.removeCallbacks(this);
    }
    
    public void post() {
      DropDownListView.this.post(this);
    }
    
    public void run() {
      DropDownListView.this.mResolveHoverRunnable = null;
      DropDownListView.this.drawableStateChanged();
    }
  }
}


/* Location:              C:\Users\15856\Desktop\2675384-dex2jar.jar!\android\support\v7\widget\DropDownListView.class
 * Java compiler version: 6 (50.0)
 * JD-Core Version:       1.1.3
 */